bitcoindevkit/__init__.py
bitcoindevkit/bitcoindevkit.py
bitcoindevkit-0.0.1.dist-info/METADATA
bitcoindevkit-0.0.1.dist-info/WHEEL
bitcoindevkit-0.0.1.dist-info/top_level.txt
bitcoindevkit-0.0.1.dist-info/RECORD
